deep_getstockinfo/GetStockInfo.py
deep_getstockinfo/__init__.py
deep_getstockinfo/deep_getstockinfo.py
deep_getstockinfo-0.1.0.dist-info/LICENSE
deep_getstockinfo-0.1.0.dist-info/METADATA
deep_getstockinfo-0.1.0.dist-info/WHEEL
deep_getstockinfo-0.1.0.dist-info/top_level.txt
deep_getstockinfo-0.1.0.dist-info/RECORD
