Metadata-Version: 2.1
Name: deep-getstockinfo
Version: 0.1.0
Summary: Get Stock Info from Web API
Home-page: https://github.com/pypa/sampleproject
Author: Zhang Yi
Author-email: zhang_yi@live.com
License: UNKNOWN
Platform: UNKNOWN
Classifier: Programming Language :: Python :: 3
Classifier: License :: OSI Approved :: MIT License
Classifier: Operating System :: OS Independent
Requires-Python: >=3.6
License-File: LICENSE
